lumen/__init__.py
lumen/_client.py
lumen/customers.py
lumen/enrollment.py
lumen/entitlements.py
lumen/events.py
lumen/exceptions.py
lumen/seats.py
lumen/subscriptions.py
lumen/types.py
lumen/handlers/__init__.py
lumen/handlers/django_handler.py
lumen/handlers/fastapi_handler.py
lumen/handlers/flask_handler.py
lumen_python_sdk-0.1.1.dist-info/METADATA
lumen_python_sdk-0.1.1.dist-info/WHEEL
lumen_python_sdk-0.1.1.dist-info/licenses/LICENSE
lumen_python_sdk-0.1.1.dist-info/RECORD
