Metadata-Version: 2.4
Name: lumen-python-sdk
Version: 0.1.1
Summary: Official Python SDK for Lumen - Payments and Billing Infrastructure
Project-URL: Homepage, https://getlumen.dev
Project-URL: Documentation, https://getlumen.dev/docs
Project-URL: Repository, https://github.com/getlumen/lumen-python-sdk
Project-URL: Issues, https://github.com/getlumen/lumen-python-sdk/issues
Author-email: Lumen Team <hello@getlumen.dev>
License: MIT
License-File: LICENSE
Keywords: billing,lumen,payments,saas,subscriptions
Classifier: Development Status :: 4 - Beta
Classifier: Intended Audience :: Developers
Classifier: License :: OSI Approved :: MIT License
Classifier: Programming Language :: Python :: 3
Classifier: Programming Language :: Python :: 3.8
Classifier: Programming Language :: Python :: 3.9
Classifier: Programming Language :: Python :: 3.10
Classifier: Programming Language :: Python :: 3.11
Classifier: Programming Language :: Python :: 3.12
Classifier: Topic :: Software Development :: Libraries :: Python Modules
Requires-Python: >=3.8
Requires-Dist: httpx>=0.24.0
Requires-Dist: typing-extensions>=4.0.0; python_version < '3.10'
Provides-Extra: dev
Requires-Dist: black>=23.0.0; extra == 'dev'
Requires-Dist: mypy>=1.0.0; extra == 'dev'
Requires-Dist: pytest-asyncio>=0.21.0; extra == 'dev'
Requires-Dist: pytest-cov>=4.0.0; extra == 'dev'
Requires-Dist: pytest>=7.0.0; extra == 'dev'
Requires-Dist: ruff>=0.1.0; extra == 'dev'
Provides-Extra: django
Requires-Dist: django>=3.2.0; extra == 'django'
Provides-Extra: fastapi
Requires-Dist: fastapi>=0.100.0; extra == 'fastapi'
Requires-Dist: starlette>=0.27.0; extra == 'fastapi'
Provides-Extra: flask
Requires-Dist: flask>=2.0.0; extra == 'flask'
